README.md
setup.cfg
setup.py
fakhrydistributions/Binomialdistribution.py
fakhrydistributions/Gaussiandistribution.py
fakhrydistributions/Generaldistribution.py
fakhrydistributions/__init__.py
fakhrydistributions.egg-info/PKG-INFO
fakhrydistributions.egg-info/SOURCES.txt
fakhrydistributions.egg-info/dependency_links.txt
fakhrydistributions.egg-info/not-zip-safe
fakhrydistributions.egg-info/top_level.txt